setup2poetry/__init__.py
setup2poetry/adapter.py
setup2poetry/cli.py
setup2poetry-0.1.1.dist-info/entry_points.txt
setup2poetry-0.1.1.dist-info/LICENSE
setup2poetry-0.1.1.dist-info/WHEEL
setup2poetry-0.1.1.dist-info/METADATA
setup2poetry-0.1.1.dist-info/RECORD
